__init__.py
notebook_orchestration_execution_manager.py
notebook_orchestration_and_execution_manager-0.2.27.13.13.dist-info/LICENSE
notebook_orchestration_and_execution_manager-0.2.27.13.13.dist-info/METADATA
notebook_orchestration_and_execution_manager-0.2.27.13.13.dist-info/WHEEL
notebook_orchestration_and_execution_manager-0.2.27.13.13.dist-info/top_level.txt
notebook_orchestration_and_execution_manager-0.2.27.13.13.dist-info/RECORD
