Metadata-Version: 2.1
Name: notebook-orchestration-and-execution-manager
Version: 0.2.27.13.13
Summary: A tool for orchestrating and executing Jupyter notebooks, enabling seamless parameter passing between notebooks.
Home-page: https://github.com/JorgeCardona/notebook-orchestration-and-execution-manager
Author: Jorge Cardona
Classifier: Programming Language :: Python :: 3
Classifier: License :: OSI Approved :: MIT License
Classifier: Operating System :: OS Independent
Requires-Python: >=3.6
License-File: LICENSE
Requires-Dist: papermill
Requires-Dist: IPython
